influential_analysis/__init__.py
influential_analysis/influential_analysis.py
influential_analysis-0.1.2.dist-info/METADATA
influential_analysis-0.1.2.dist-info/WHEEL
influential_analysis-0.1.2.dist-info/top_level.txt
influential_analysis-0.1.2.dist-info/RECORD
